Metadata-Version: 2.1
Name: ds-2023-calc-pack
Version: 1.0.0
Summary: A calculator package for performing basic math operations.
Home-page: https://github.com/TuringCollegeSubmissions/lsitsh-DWWP.1/tree/master/calculator-package
Author: Lenara Sitshayeva
Author-email: sitshayeva@gmail.com
License: UNKNOWN
Platform: UNKNOWN
Classifier: Development Status :: 5 - Production/Stable
Classifier: Intended Audience :: Developers
Classifier: Operating System :: OS Independent
Classifier: Programming Language :: Python
Classifier: Programming Language :: Python :: 3
Classifier: Programming Language :: Python :: 3.6
Classifier: Programming Language :: Python :: 3.7
Classifier: Programming Language :: Python :: 3.8
Requires-Python: >=3.6
